Workbook

Sheet Instructions
A1: Northbank Freight Services: NIST CSF 2.0 Risk Assessment and Risk Register
A2: Fictional training scenario. Analyst: Waseem Akram Shaik. The company, people and findings are made up for practice.
A4: HOW TO USE THIS WORKBOOK
A5: 1. Scoring Method: read the scales and thresholds. Rating thresholds are assumption cells (yellow); change them there and every rating updates.
A6: 2. Assets: rate each asset's criticality (1-5) and write one line of why.
A7: 3. CSF Gap Assessment: for each of the 22 CSF 2.0 categories, enter current and target maturity (0-4) and the evidence IDs (F-01 etc.) behind your score.
A8: 4. Risk Register: one row per risk. Fill the yellow cells. Scores, ratings and priority calculate automatically.
A9: 5. Summary: nothing to type. It counts your register and gap scores. Check that the numbers look right.
A11: LEGEND
A12: Yellow cells = you fill in. White cells with black text = formulas, do not overwrite. Grey = reference text.
A14: EXAMPLE ROW (for format only; write your own wording and do not copy it)
A15: Risk title | B15: Email accounts taken over through stolen passwords
A16: Evidence IDs | B16: F-01, F-06
A17: Risk statement | B17: Because 137 of 140 email users sign in with a password only and staff have entered credentials on fake pages before, an attacker who phishes a password could read mail and impersonate staff, leading to fraudulent payment requests and exposure of customer data.
A18: CSF category | B18: PR.AA (Identity Management, Authentication, and Access Control)
A19: Likelihood / Impact | B19: 4 (Likely) / 4 (Major) = 16, rating High
A20: Why those scores | B20: Likelihood 4: credential phishing already succeeded in the past year and MFA is absent for most users. Impact 4: fraud and customer data exposure could cost more than $250k and risk contracts.
A21: Treatment | B21: Mitigate: enforce MFA for all users (also required by the Jan 2027 cyber insurance renewal).

Sheet Scoring Method
A1: Likelihood scale (12-month view, analyst judgement, not statistics)
A2: Score | B2: Label | C2: Meaning
A3: 1 | B3: Rare | C3: Under 5% chance in 12 months
A4: 2 | B4: Unlikely | C4: 5% to 20%
A5: 3 | B5: Possible | C5: 20% to 50%
A6: 4 | B6: Likely | C6: 50% to 80%
A7: 5 | B7: Almost certain | C7: Over 80%, or it has already happened
A9: Impact scale (worst realistic outcome; dollar ranges are assumptions for this fictional company)
A10: Score | B10: Label | C10: Meaning
A11: 1 | B11: Minor | C11: Under 4 hours of disruption; no data exposed; under $10,000
A12: 2 | B12: Moderate | C12: Up to 1 day disruption; limited internal data exposed; $10,000 to $50,000
A13: 3 | B13: Significant | C13: 1 to 3 days disruption; some personal data exposed; $50,000 to $250,000
A14: 4 | B14: Major | C14: 3 to 7 days disruption; large personal data exposure or loss of a key customer; $250,000 to $1,000,000
A15: 5 | B15: Severe | C15: Over 1 week disruption; large exposure with legal or regulatory consequences; over $1,000,000
A17: Rating thresholds (score = likelihood x impact, range 1 to 25). Minimum score for each rating:
A18: Rating | B18: Minimum score | C18: Meaning
A19: Low | B19: 1 | C19: Accept or monitor
A20: Medium | B20: 6 | C20: Plan treatment within 90 days
A21: High | B21: 12 | C21: Treat within 60 days
A22: Critical | B22: 20 | C22: Treat within 30 days
A24: Assumption: thresholds are common 5x5 matrix choices, not a NIST requirement. Blue text on yellow = an input you may change.
A26: CSF maturity scale used in the gap assessment (a simple scale of my own; CSF 2.0 does not prescribe per-category scores)
A27: Score | B27: Label | C27: Meaning
A28: 0 | B28: Not in place | C28: Nothing exists
A29: 1 | B29: Ad hoc | C29: Done informally or by one person; no document
A30: 2 | B30: Partial | C30: Documented or tool-supported but inconsistent or incomplete
A31: 3 | B31: Defined | C31: Documented, owned and applied consistently
A32: 4 | B32: Managed | C32: Measured, reviewed on a schedule and improved

Sheet Assets
A1: Asset ID | B1: Asset | C1: Type | D1: Owner (role) | E1: What it holds or does | F1: Criticality (1-5) | G1: Why this criticality (your words)
A2: A-01 | B2: Microsoft 365 tenant (email, Teams, OneDrive) | C2: SaaS | D2: IT Manager | E2: Email, chat and document sharing for all 140 staff | F2: 5 | G2: All 140 staff depend on it for email, chat and files, and a takeover or outage would stop most office work.
A3: A-02 | B3: RouteLine TMS (cloud transport management system) | C3: SaaS | D3: Operations Director | E3: Load booking, carrier rates and customer shipments | F3: 4 | G3: It books loads and holds carrier rates and shipments, but the vendor runs it under a 99.5% uptime contract.
A4: A-03 | B4: StockWise WMS server (Windows Server 2012 R2) | C4: On-premises server | D4: IT Manager | E4: Warehouse inventory and shipping; runs the warehouse | F4: 5 | G4: It runs the warehouse, and operations can work manually for only about 4 hours before shipments are delayed.
A5: A-04 | B5: File server | C5: On-premises server | D5: IT Manager | E5: Customer contracts, driver documents, payroll exports | F5: 4 | G5: It holds customer contracts, driver documents and payroll exports, but the business can work for a while without it.
A6: A-05 | B6: Backup NAS | C6: On-premises storage | D6: System Administrator | E6: Nightly backups of servers and file shares | F6: 4 | G6: It is the main way to recover after ransomware or a failure, so losing it removes the safety net.
A7: A-06 | B7: Office and warehouse network (firewall, switches, Wi-Fi) | C7: Network | D7: System Administrator | E7: Connects offices, warehouse, scanners and vendor VPN | F7: 5 | G7: The scanners, WMS server, offices and partner VPN all depend on it.
A8: A-07 | B8: Employee laptops (85) | C8: Endpoint | D8: System Administrator | E8: Staff work devices, some used while travelling | F8: 3 | G8: They are needed for daily work, but each one is replaceable and data is mostly on servers and cloud.
A9: A-08 | B9: Handheld barcode scanners (30) | C9: Endpoint | D9: Warehouse Manager | E9: Scan inventory and shipments into the WMS | F9: 3 | G9: The warehouse needs them to scan goods, but they are cheap and replaceable, and the data sits in the WMS.
A10: A-09 | B10: EDI site-to-site VPN to partner | C10: Network / third party | D10: IT Manager | E10: Exchanges orders with a 3PL partner | F10: 3 | G10: It carries orders for one partner, so an outage hurts that partner's work but not the whole business.
A11: A-10 | B11: Payroll provider portal (outsourced) | C11: SaaS / third party | D11: HR Manager | E11: Employee pay and tax data | F11: 3 | G11: A problem delays pay and exposes pay data, but the provider runs and secures the system.
A12: A-11 | B12: Driver and employee personal data (licenses, SSNs) | C12: Data | D12: HR Manager | E12: Stored on the file server and in payroll exports | F12: 5 | G12: Driver license copies and Social Security numbers cannot be un-leaked, and a breach brings legal, notice and trust costs.
A13: A-12 | B13: Customer contracts and pricing | C13: Data | D13: Commercial Director | E13: Contract terms and rates | F13: 4 | G13: Exposure would hurt pricing power and customer trust, and some contracts require reasonable security.
... A15: A-14 | B15: Microsoft Defender endpoint protection | C15: Security tool | D15: System Administrator | E15: Antivirus and basic endpoint alerts | F15: 2 | G15: It is a protective tool and not a business asset, so losing it raises risk elsewhere without stopping operations.

Sheet CSF Gap Assessment
A1: CSF 2.0 Function | B1: Category ID | C1: Category name | D1: Current maturity (0-4) | E1: Target maturity (0-4) | F1: Gap | G1: Evidence IDs | H1: Notes (why you scored it this way)
A2: GOVERN | B2: GV.OC | C2: Organizational Context | D2: 2 | E2: 3 | F2: =IF(OR(D2="",E2=""),"",E2-D2) -> 1 | G2: F-15 | H2: The company knows its business priorities, customer security terms and the January 2027 insurance requirement, but cyber is not tied into leadership decisions.
A3: GOVERN | B3: GV.RM | C3: Risk Management Strategy | D3: 1 | E3: 3 | F3: =IF(OR(D3="",E3=""),"",E3-D3) -> 2 | G3: F-15 | H3: No named risk owner, no risk reporting to executives and no separate cyber budget; risk is handled informally.
A4: GOVERN | B4: GV.RR | C4: Roles, Responsibilities, and Authorities | D4: 1 | E4: 3 | F4: =IF(OR(D4="",E4=""),"",E4-D4) -> 2 | G4: F-15, F-08 | H4: No named risk owner and the incident plan lists a former employee, so roles are unclear.
A5: GOVERN | B5: GV.PO | C5: Policy | D5: 2 | E5: 3 | F5: =IF(OR(D5="",E5=""),"",E5-D5) -> 1 | G5: F-02, F-08 | H5: A password policy and a 2021 incident plan exist, but they are thin and out of date. No other policies were shown.
A6: GOVERN | B6: GV.OV | C6: Oversight | D6: 0 | E6: 2 | F6: =IF(OR(D6="",E6=""),"",E6-D6) -> 2 | G6: F-15 | H6: No evidence of cyber oversight or review by leadership.
A7: GOVERN | B7: GV.SC | C7: Cybersecurity Supply Chain Risk Management | D7: 1 | E7: 3 | F7: =IF(OR(D7="",E7=""),"",E7-D7) -> 2 | G7: F-13, F-09 | H7: 12 vendors with no security checks or contract review, and a partner VPN never reviewed since 2019.
A8: IDENTIFY | B8: ID.AM | C8: Asset Management | D8: 1 | E8: 3 | F8: =IF(OR(D8="",E8=""),"",E8-D8) -> 2 | G8: F-03 | H8: No central inventory; laptops are tracked in a spreadsheet updated when someone remembers, and scanners are not tracked.
A9: IDENTIFY | B9: ID.RA | C9: Risk Assessment | D9: 1 | E9: 3 | F9: =IF(OR(D9="",E9=""),"",E9-D9) -> 2 | G9: F-04, F-15 | H9: Known issues such as the unsupported WMS server are discussed informally, but there is no risk assessment process.
A10: IDENTIFY | B10: ID.IM | C10: Improvement | D10: 1 | E10: 2 | F10: =IF(OR(D10="",E10=""),"",E10-D10) -> 1 | G10: F-08 | H10: The incident plan has never been tested and there is no review step after incidents.
A11: PROTECT | B11: PR.AA | C11: Identity Management, Authentication, and Access Control | D11: 1 | E11: 3 | F11: =IF(OR(D11="",E11=""),"",E11-D11) -> 2 | G11: F-01, F-02, F-11, F-16, F-19 | H11: MFA covers 3 of 140 users, weak password rules, a shared scanner login, leavers keeping access, and an internet-exposed Remote Desktop.
A12: PROTECT | B12: PR.AT | C12: Awareness and Training | D12: 2 | E12: 3 | F12: =IF(OR(D12="",E12=""),"",E12-D12) -> 1 | G12: F-06 | H12: Annual training exists, but only one video, with no phishing simulations, and 3 credential-entry incidents happened last year.
A13: PROTECT | B13: PR.DS | C13: Data Security | D13: 1 | E13: 3 | F13: =IF(OR(D13="",E13=""),"",E13-D13) -> 2 | G13: F-10, F-14, F-05 | H13: 25 of 85 laptops unencrypted, sensitive files open to Domain Users, and backups held on the same network.
... A23: RECOVER | B23: RC.CO | C23: Incident Recovery Communication | D23: 0 | E23: 2 | F23: =IF(OR(D23="",E23=""),"",E23-D23) -> 2 | G23: None provided | H23: No evidence of any recovery communication plan.
A25: Source for category IDs and names: NIST Cybersecurity Framework 2.0 (nist.gov/cyberframework). Maturity scores use the scale on the Scoring Method sheet.

Sheet Risk Register
A1: Risk ID | B1: Risk title | C1: Asset ID(s) | D1: Evidence ID(s) | E1: Risk statement (cause, event, impact) | F1: CSF Function | G1: CSF Category | H1: Likelihood (1-5) | I1: Impact (1-5) | J1: Inherent score | K1: Inherent rating | L1: Existing controls | M1: Treatment | N1: Recommended action | O1: Owner (role) | P1: Priority | Q1: Residual likelihood | R1: Residual impact | S1: Residual score | T1: Residual rating | U1: Scoring rationale (why these scores)
A2: R-01 | B2: Internet-exposed Remote Desktop leads to ransomware | C2: A-04, A-05, A-11, A-12 | D2: F-19, F-05, F-02, F-14 | E2: Because Remote Desktop to the file server is reachable from the internet, passwords are weak with no lockout, and backups sit on the same network, an attacker could guess or buy a password, encrypt or steal the file server's data and reach the backups, leading to days of lost work, exposure of driver SSNs and licenses, and customer contract risk. | F2: PROTECT | G2: PR.IR | H2: 4 | I2: 5 | J2: =IF(OR(H2="",I2=""),"",H2*I2) -> 20 | K2: =IF(J2="","",IF(J2>='Scoring Method'!$B$22,"Critical",IF(J2>='Scoring Method'!$B$21,"High",IF(J2>='Scoring Method'!$B$20,"Medium","Low")))) -> Critical | L2: Defender on laptops (alerts unread); nightly backups to a NAS on the same network, never restore-tested | M2: Mitigate | N2: Close the Remote Desktop port forward now; require a VPN with MFA for remote access; set account lockout; review all firewall rules. | O2: IT Manager | P2: =IF(K2="","",IF(K2="Critical","Immediate (30 days)",IF(K2="High","Short term (60 days)",IF(K2="Medium","Medium term (90 days)","Monitor")))) -> Immediate (30 days) | Q2: 2 | R2: 4 | S2: =IF(OR(Q2="",R2=""),"",Q2*R2) -> 8 | T2: =IF(S2="","",IF(S2>='Scoring Method'!$B$22,"Critical",IF(S2>='Scoring Method'!$B$21,"High",IF(S2>='Scoring Method'!$B$20,"Medium","Low")))) -> Medium | U2: Likelihood 4: internet-facing Remote Desktop is scanned constantly, there is no lockout (F-02) and the rule has not been reviewed since 2023 (F-19). Impact 5: ransomware or theft would hit personal data, contracts and the backups (F-05), and the flat network could let it spread. Residual impact stays 4 until backups are fixed under R-04.
A3: R-02 | B3: Unsupported warehouse server fails or is compromised | C3: A-03, A-06, A-09 | D3: F-04, F-09, F-12, F-20 | E3: Because the warehouse management server runs Windows Server 2012 R2 with no security updates, sits on a flat network reachable from the partner VPN, and operations can work manually for only about 4 hours, an attacker or a failure could take the server down, leading to delayed shipments, missed customer commitments and lost revenue for several days. | F3: PROTECT | G3: PR.PS | H3: 3 | I3: 4 | J3: =IF(OR(H3="",I3=""),"",H3*I3) -> 12 | K3: =IF(J3="","",IF(J3>='Scoring Method'!$B$22,"Critical",IF(J3>='Scoring Method'!$B$21,"High",IF(J3>='Scoring Method'!$B$20,"Medium","Low")))) -> High | L3: Nightly backup of the server exists but is untested; no vendor patches are available | M3: Mitigate | N3: Put the server in its own network segment and allow only what the warehouse needs; limit partner VPN access to specific systems; run a restore test; plan migration before the 2028 vendor date. | O3: IT Manager (with the WMS vendor) | P3: =IF(K3="","",IF(K3="Critical","Immediate (30 days)",IF(K3="High","Short term (60 days)",IF(K3="Medium","Medium term (90 days)","Monitor")))) -> Short term (60 days) | Q3: 2 | R3: 4 | S3: =IF(OR(Q3="",R3=""),"",Q3*R3) -> 8 | T3: =IF(S3="","",IF(S3>='Scoring Method'!$B$22,"Critical",IF(S3>='Scoring Method'!$B$21,"High",IF(S3>='Scoring Method'!$B$20,"Medium","Low")))) -> Medium | U3: Likelihood 3: it is unpatched and reachable from the VPN, but not directly exposed to the internet like R-01. Impact 4: it is the core of warehouse operations, and rebuilding an old system with no vendor upgrade path would likely take days (F-20).
A4: R-03 | B4: Email accounts taken over because MFA is missing for most users | C4: A-01 | D4: F-01, F-02, F-06 | E4: Because 137 of 140 email users sign in with a password only, passwords are weak and staff have entered credentials on fake pages before, an attacker who phishes a password could read mail and impersonate staff, leading to fraudulent payment requests, customer data exposure and loss of the cyber insurance renewal terms. | F4: PROTECT | G4: PR.AA | H4: 4 | I4: 4 | J4: =IF(OR(H4="",I4=""),"",H4*I4) -> 16 | K4: =IF(J4="","",IF(J4>='Scoring Method'!$B$22,"Critical",IF(J4>='Scoring Method'!$B$21,"High",IF(J4>='Scoring Method'!$B$20,"Medium","Low")))) -> High | L4: MFA for the 3 global administrators; annual awareness video | M4: Mitigate | N4: Enforce MFA for all Microsoft 365 users with Conditional Access; strengthen the password policy and add lockout; add phishing simulations. | O4: IT Manager | P4: =IF(K4="","",IF(K4="Critical","Immediate (30 days)",IF(K4="High","Short term (60 days)",IF(K4="Medium","Medium term (90 days)","Monitor")))) -> Short term (60 days) | Q4: 2 | R4: 3 | S4: =IF(OR(Q4="",R4=""),"",Q4*R4) -> 6 | T4: =IF(S4="","",IF(S4>='Scoring Method'!$B$22,"Critical",IF(S4>='Scoring Method'!$B$21,"High",IF(S4>='Scoring Method'!$B$20,"Medium","Low")))) -> Medium | U4: Likelihood 4: credential-entry incidents already happened 3 times last year (F-06) and MFA covers 3 of 140 users (F-01). Impact 4: fraud and customer data exposure could pass $250,000 and put contracts at risk. After MFA, impact falls to 3 because a stolen password alone no longer opens the account.
A5: R-04 | B5: Backups unusable when needed | C5: A-05, A-04, A-03 | D5: F-05, F-20 | E5: Because backups are stored on the same network as the servers, an administrator share stays mapped, restores have never been tested and there is no offline copy, ransomware or a hardware failure could destroy or encrypt the backups, leading to a recovery that takes more than a week or loses data permanently. | F5: RECOVER | G5: RC.RP | H5: 3 | I5: 5 | J5: =IF(OR(H5="",I5=""),"",H5*I5) -> 15 | K5: =IF(J5="","",IF(J5>='Scoring Method'!$B$22,"Critical",IF(J5>='Scoring Method'!$B$21,"High",IF(J5>='Scoring Method'!$B$20,"Medium","Low")))) -> High | L5: Nightly backups to a NAS | M5: Mitigate | N5: Add an offline or immutable off-site copy; remove the mapped admin share; test a restore quarterly; set recovery time and recovery point targets. | O5: System Administrator | P5: =IF(K5="","",IF(K5="Critical","Immediate (30 days)",IF(K5="High","Short term (60 days)",IF(K5="Medium","Medium term (90 days)","Monitor")))) -> Short term (60 days) | Q5: 2 | R5: 3 | S5: =IF(OR(Q5="",R5=""),"",Q5*R5) -> 6 | T5: =IF(S5="","",IF(S5>='Scoring Method'!$B$22,"Critical",IF(S5>='Scoring Method'!$B$21,"High",IF(S5>='Scoring Method'!$B$20,"Medium","Low")))) -> Medium | U5: Likelihood 3: a failure or attack that needs the backups is possible, and untested backups often fail (F-05). Impact 5: without a working backup the company could lose data and be down for over a week. The insurer will also require tested backups.
A6: R-05 | B6: Departed staff and shared logins misused | C6: A-01, A-08 | D6: F-16, F-11 | E6: Because 3 of 10 recent leavers still had active accounts after 30 days and all 30 scanners share one login known to every shift worker, a former employee or contractor could sign in without being traced, leading to data theft, unauthorized changes to warehouse records or an investigation that cannot name who did it. | F6: PROTECT | G6: PR.AA | H6: 4 | I6: 3 | J6: =IF(OR(H6="",I6=""),"",H6*I6) -> 12 | K6: =IF(J6="","",IF(J6>='Scoring Method'!$B$22,"Critical",IF(J6>='Scoring Method'!$B$21,"High",IF(J6>='Scoring Method'!$B$20,"Medium","Low")))) -> High | L6: Access removal relies on HR emailing IT | M6: Mitigate | N6: Disable accounts on the leaving date through an HR-to-IT checklist; issue individual scanner logins; change the warehouse Wi-Fi password and use a separate guest network for contractors. | O6: HR Manager and IT Manager | P6: =IF(K6="","",IF(K6="Critical","Immediate (30 days)",IF(K6="High","Short term (60 days)",IF(K6="Medium","Medium term (90 days)","Monitor")))) -> Short term (60 days) | Q6: 2 | R6: 2 | S6: =IF(OR(Q6="",R6=""),"",Q6*R6) -> 4 | T6: =IF(S6="","",IF(S6>='Scoring Method'!$B$22,"Critical",IF(S6>='Scoring Method'!$B$21,"High",IF(S6>='Scoring Method'!$B$20,"Medium","Low")))) -> Low | U6: Likelihood 4: the problem was seen in 3 of 10 leavers and the shared login is known to everyone (F-16, F-11). Impact 3: access to systems and some data, but not the most sensitive stores by itself.
A7: R-06 | B7: Partner VPN becomes a path into the warehouse network | C7: A-09, A-06 | D7: F-09, F-13 | E7: Because a partner's VPN has had unreviewed access to a flat network since 2019 and vendors are not checked for security, a compromise at the partner could be used to reach the warehouse systems, leading to downtime and exposure of operational data. | F7: GOVERN | G7: GV.SC | H7: 2 | I7: 4 | J7: =IF(OR(H7="",I7=""),"",H7*I7) -> 8 | K7: =IF(J7="","",IF(J7>='Scoring Method'!$B$22,"Critical",IF(J7>='Scoring Method'!$B$21,"High",IF(J7>='Scoring Method'!$B$20,"Medium","Low")))) -> Medium | L7: Site-to-site VPN with the partner; no review since 2019 | M7: Mitigate | N7: Review and limit the VPN to the systems the partner needs; add a security clause and annual access review to the partner contract; segment the network. | O7: IT Manager | P7: =IF(K7="","",IF(K7="Critical","Immediate (30 days)",IF(K7="High","Short term (60 days)",IF(K7="Medium","Medium term (90 days)","Monitor")))) -> Medium term (90 days) | Q7: 1 | R7: 4 | S7: =IF(OR(Q7="",R7=""),"",Q7*R7) -> 4 | T7: =IF(S7="","",IF(S7>='Scoring Method'!$B$22,"Critical",IF(S7>='Scoring Method'!$B$21,"High",IF(S7>='Scoring Method'!$B$20,"Medium","Low")))) -> Low | U7: Likelihood 2: it needs the partner to be compromised first, which is less probable than a direct attack. Impact 4: access to the warehouse network could stop operations.
A8: R-07 | B8: An attack goes unnoticed because nobody watches logs or alerts | C8: A-14, A-06 | D8: F-07, F-17 | E8: Because firewall logs are kept for only 7 days, there is no central logging and Defender alerts go to a mailbox nobody reads daily, an intruder could stay undetected for weeks, leading to larger data theft and no evidence for investigation or insurance claims. | F8: DETECT | G8: DE.CM | H8: 4 | I8: 3 | J8: =IF(OR(H8="",I8=""),"",H8*I8) -> 12 | K8: =IF(J8="","",IF(J8>='Scoring Method'!$B$22,"Critical",IF(J8>='Scoring Method'!$B$21,"High",IF(J8>='Scoring Method'!$B$20,"Medium","Low")))) -> High | L8: Microsoft Defender on laptops; alerts sent to a shared mailbox | M8: Mitigate | N8: Route Defender and Microsoft 365 sign-in alerts to named people with a daily review; extend log retention to at least 90 days; evaluate a low-cost central logging or managed monitoring service. | O8: System Administrator | P8: =IF(K8="","",IF(K8="Critical","Immediate (30 days)",IF(K8="High","Short term (60 days)",IF(K8="Medium","Medium term (90 days)","Monitor")))) -> Short term (60 days) | Q8: 2 | R8: 3 | S8: =IF(OR(Q8="",R8=""),"",Q8*R8) -> 6 | T8: =IF(S8="","",IF(S8>='Scoring Method'!$B$22,"Critical",IF(S8>='Scoring Method'!$B$21,"High",IF(S8>='Scoring Method'!$B$20,"Medium","Low")))) -> Medium | U8: Likelihood 4: no one is positioned to notice an attack today (F-17). Impact 3: this risk makes other incidents longer and worse rather than causing harm by itself.
A9: R-08 | B9: Weak incident response slows containment | C9: A-01, A-03, A-04 | D9: F-08 | E9: Because the incident response plan is a 2021 two-page document with no defined roles, no exercise and a former employee as contact, a real incident could be handled slowly or wrongly, leading to longer downtime and missed customer or insurer notification deadlines. | F9: RESPOND | G9: RS.MA | H9: 3 | I9: 3 | J9: =IF(OR(H9="",I9=""),"",H9*I9) -> 9 | K9: =IF(J9="","",IF(J9>='Scoring Method'!$B$22,"Critical",IF(J9>='Scoring Method'!$B$21,"High",IF(J9>='Scoring Method'!$B$20,"Medium","Low")))) -> Medium | L9: A 2-page plan from 2021 | M9: Mitigate | N9: Update the plan with named roles and current contacts; run a short tabletop exercise each year; add customer and insurer notification steps. | O9: IT Manager | P9: =IF(K9="","",IF(K9="Critical","Immediate (30 days)",IF(K9="High","Short term (60 days)",IF(K9="Medium","Medium term (90 days)","Monitor")))) -> Medium term (90 days) | Q9: 2 | R9: 2 | S9: =IF(OR(Q9="",R9=""),"",Q9*R9) -> 4 | T9: =IF(S9="","",IF(S9>='Scoring Method'!$B$22,"Critical",IF(S9>='Scoring Method'!$B$21,"High",IF(S9>='Scoring Method'!$B$20,"Medium","Low")))) -> Low | U9: Likelihood 3: an incident is possible, and the weak plan raises the chance it goes badly. Impact 3: longer outages and notification problems, but a bad plan does not cause the incident itself.
A10: R-09 | B10: Lost or stolen unencrypted laptop | C10: A-07, A-11 | D10: F-10 | E10: Because 25 of 85 laptops, including 8 used by travelling sales staff, are not encrypted, a lost or stolen laptop could expose any customer or employee files stored on it, leading to a notification obligation and loss of customer trust. | F10: PROTECT | G10: PR.DS | H10: 3 | I10: 3 | J10: =IF(OR(H10="",I10=""),"",H10*I10) -> 9 | K10: =IF(J10="","",IF(J10>='Scoring Method'!$B$22,"Critical",IF(J10>='Scoring Method'!$B$21,"High",IF(J10>='Scoring Method'!$B$20,"Medium","Low")))) -> Medium | L10: Some laptops (60 of 85) have disk encryption | M10: Mitigate | N10: Turn on BitLocker on all laptops, starting with the 8 travelling sales laptops, and report compliance monthly. | O10: System Administrator | P10: =IF(K10="","",IF(K10="Critical","Immediate (30 days)",IF(K10="High","Short term (60 days)",IF(K10="Medium","Medium term (90 days)","Monitor")))) -> Medium term (90 days) | Q10: 3 | R10: 1 | S10: =IF(OR(Q10="",R10=""),"",Q10*R10) -> 3 | T10: =IF(S10="","",IF(S10>='Scoring Method'!$B$22,"Critical",IF(S10>='Scoring Method'!$B$21,"High",IF(S10>='Scoring Method'!$B$20,"Medium","Low")))) -> Low | U10: Likelihood 3: travelling staff lose laptops at a realistic rate. Impact 3: some personal or contract data could be exposed. Once encrypted, the impact of a lost laptop drops to 1 because the data cannot be read.
A11: R-10 | B11: Sensitive data open to too many staff | C11: A-04, A-11, A-12 | D11: F-14 | E11: Because folders with driver licenses, payroll exports and contracts are readable by all domain users and nothing is classified, a curious employee or a compromised account could read or copy sensitive data, leading to a privacy incident and breach of customer contracts. | F11: PROTECT | G11: PR.DS | H11: 3 | I11: 3 | J11: =IF(OR(H11="",I11=""),"",H11*I11) -> 9 | K11: =IF(J11="","",IF(J11>='Scoring Method'!$B$22,"Critical",IF(J11>='Scoring Method'!$B$21,"High",IF(J11>='Scoring Method'!$B$20,"Medium","Low")))) -> Medium | L11: Standard file server permissions (broad group access) | M11: Mitigate | N11: Move sensitive folders to restricted groups; classify data into 3 levels; review access every quarter. | O11: IT Manager | P11: =IF(K11="","",IF(K11="Critical","Immediate (30 days)",IF(K11="High","Short term (60 days)",IF(K11="Medium","Medium term (90 days)","Monitor")))) -> Medium term (90 days) | Q11: 2 | R11: 2 | S11: =IF(OR(Q11="",R11=""),"",Q11*R11) -> 4 | T11: =IF(S11="","",IF(S11>='Scoring Method'!$B$22,"Critical",IF(S11>='Scoring Method'!$B$21,"High",IF(S11>='Scoring Method'!$B$20,"Medium","Low")))) -> Low | U11: Likelihood 3: any compromised account today can see everything. Impact 3: some personal data and contract terms would be exposed.
A12: R-11 | B12: Unpatched laptops exploited | C12: A-07 | D12: F-12, F-17 | E12: Because patching is manual with no reporting and 5 of 20 sampled laptops missed the last two updates, malware could exploit a known weakness on a laptop, leading to an infected device and a possible spread into the network. | F12: PROTECT | G12: PR.PS | H12: 3 | I12: 3 | J12: =IF(OR(H12="",I12=""),"",H12*I12) -> 9 | K12: =IF(J12="","",IF(J12>='Scoring Method'!$B$22,"Critical",IF(J12>='Scoring Method'!$B$21,"High",IF(J12>='Scoring Method'!$B$20,"Medium","Low")))) -> Medium | L12: Manual monthly patching; Defender | M12: Mitigate | N12: Use Windows Update for Business or Intune to patch automatically and report compliance; check missing patches monthly. | O12: System Administrator | P12: =IF(K12="","",IF(K12="Critical","Immediate (30 days)",IF(K12="High","Short term (60 days)",IF(K12="Medium","Medium term (90 days)","Monitor")))) -> Medium term (90 days) | Q12: 2 | R12: 2 | S12: =IF(OR(Q12="",R12=""),"",Q12*R12) -> 4 | T12: =IF(S12="","",IF(S12>='Scoring Method'!$B$22,"Critical",IF(S12>='Scoring Method'!$B$21,"High",IF(S12>='Scoring Method'!$B$20,"Medium","Low")))) -> Low | U12: Likelihood 3: a quarter of the sampled laptops were behind, so known flaws exist. Impact 3: a single infected laptop can lead to wider problems, but Defender provides some protection.
A13: R-12 | B13: Vendor weakness exposes the company | C13: A-02, A-10 | D13: F-13 | E13: Because none of 12 vendors was assessed for security and contracts were not checked for breach notification terms, a breach at the transport system or payroll vendor could expose company data without the company hearing about it, leading to a delayed response and potential contract penalties. | F13: GOVERN | G13: GV.SC | H13: 2 | I13: 3 | J13: =IF(OR(H13="",I13=""),"",H13*I13) -> 6 | K13: =IF(J13="","",IF(J13>='Scoring Method'!$B$22,"Critical",IF(J13>='Scoring Method'!$B$21,"High",IF(J13>='Scoring Method'!$B$20,"Medium","Low")))) -> Medium | L13: Vendor contracts and the TMS uptime guarantee | M13: Mitigate | N13: Send a short security questionnaire to the 5 most important vendors; add breach-notification terms at renewal; keep a vendor list with an owner. | O13: IT Manager | P13: =IF(K13="","",IF(K13="Critical","Immediate (30 days)",IF(K13="High","Short term (60 days)",IF(K13="Medium","Medium term (90 days)","Monitor")))) -> Medium term (90 days) | Q13: 2 | R13: 2 | S13: =IF(OR(Q13="",R13=""),"",Q13*R13) -> 4 | T13: =IF(S13="","",IF(S13>='Scoring Method'!$B$22,"Critical",IF(S13>='Scoring Method'!$B$21,"High",IF(S13>='Scoring Method'!$B$20,"Medium","Low")))) -> Low | U13: Likelihood 2: major vendors usually have their own controls. Impact 3: exposure of company or employee data, but only part of the business is affected.
... A15: R-14 | B15: No leadership oversight leads to missed insurance requirements | C15: A-01, A-05 | D15: F-15 | E15: Because no one owns cyber risk, executives receive no reports and cyber spending is not tracked, the company could miss the January 2027 insurer requirements for MFA and tested backups, leading to higher premiums, reduced coverage or a denied claim. | F15: GOVERN | G15: GV.RM | H15: 4 | I15: 3 | J15: =IF(OR(H15="",I15=""),"",H15*I15) -> 12 | K15: =IF(J15="","",IF(J15>='Scoring Method'!$B$22,"Critical",IF(J15>='Scoring Method'!$B$21,"High",IF(J15>='Scoring Method'!$B$20,"Medium","Low")))) -> High | L15: Cyber insurance policy; IT Manager handles security informally | M15: Mitigate | N15: Name an executive risk owner; report quarterly on this risk register; set a budget line; track MFA and backup tests as renewal requirements. | O15: Executive team (named risk owner) | P15: =IF(K15="","",IF(K15="Critical","Immediate (30 days)",IF(K15="High","Short term (60 days)",IF(K15="Medium","Medium term (90 days)","Monitor")))) -> Short term (60 days) | Q15: 2 | R15: 3 | S15: =IF(OR(Q15="",R15=""),"",Q15*R15) -> 6 | T15: =IF(S15="","",IF(S15>='Scoring Method'!$B$22,"Critical",IF(S15>='Scoring Method'!$B$21,"High",IF(S15>='Scoring Method'!$B$20,"Medium","Low")))) -> Medium | U15: Likelihood 4: MFA and tested backups are not in place and the renewal is in January 2027. Impact 3: higher cost or reduced coverage, estimated at $50,000 to $250,000 under the assumed scale.
A16: R-15 | J16: =IF(OR(H16="",I16=""),"",H16*I16) | K16: =IF(J16="","",IF(J16>='Scoring Method'!$B$22,"Critical",IF(J16>='Scoring Method'!$B$21,"High",IF(J16>='Scoring Method'!$B$20,"Medium","Low")))) | P16: =IF(K16="","",IF(K16="Critical","Immediate (30 days)",IF(K16="High","Short term (60 days)",IF(K16="Medium","Medium term (90 days)","Monitor")))) | S16: =IF(OR(Q16="",R16=""),"",Q16*R16) | T16: =IF(S16="","",IF(S16>='Scoring Method'!$B$22,"Critical",IF(S16>='Scoring Method'!$B$21,"High",IF(S16>='Scoring Method'!$B$20,"Medium","Low"))))
A17: R-16 | J17: =IF(OR(H17="",I17=""),"",H17*I17) | K17: =IF(J17="","",IF(J17>='Scoring Method'!$B$22,"Critical",IF(J17>='Scoring Method'!$B$21,"High",IF(J17>='Scoring Method'!$B$20,"Medium","Low")))) | P17: =IF(K17="","",IF(K17="Critical","Immediate (30 days)",IF(K17="High","Short term (60 days)",IF(K17="Medium","Medium term (90 days)","Monitor")))) | S17: =IF(OR(Q17="",R17=""),"",Q17*R17) | T17: =IF(S17="","",IF(S17>='Scoring Method'!$B$22,"Critical",IF(S17>='Scoring Method'!$B$21,"High",IF(S17>='Scoring Method'!$B$20,"Medium","Low"))))
A18: R-17 | J18: =IF(OR(H18="",I18=""),"",H18*I18) | K18: =IF(J18="","",IF(J18>='Scoring Method'!$B$22,"Critical",IF(J18>='Scoring Method'!$B$21,"High",IF(J18>='Scoring Method'!$B$20,"Medium","Low")))) | P18: =IF(K18="","",IF(K18="Critical","Immediate (30 days)",IF(K18="High","Short term (60 days)",IF(K18="Medium","Medium term (90 days)","Monitor")))) | S18: =IF(OR(Q18="",R18=""),"",Q18*R18) | T18: =IF(S18="","",IF(S18>='Scoring Method'!$B$22,"Critical",IF(S18>='Scoring Method'!$B$21,"High",IF(S18>='Scoring Method'!$B$20,"Medium","Low"))))
A19: R-18 | J19: =IF(OR(H19="",I19=""),"",H19*I19) | K19: =IF(J19="","",IF(J19>='Scoring Method'!$B$22,"Critical",IF(J19>='Scoring Method'!$B$21,"High",IF(J19>='Scoring Method'!$B$20,"Medium","Low")))) | P19: =IF(K19="","",IF(K19="Critical","Immediate (30 days)",IF(K19="High","Short term (60 days)",IF(K19="Medium","Medium term (90 days)","Monitor")))) | S19: =IF(OR(Q19="",R19=""),"",Q19*R19) | T19: =IF(S19="","",IF(S19>='Scoring Method'!$B$22,"Critical",IF(S19>='Scoring Method'!$B$21,"High",IF(S19>='Scoring Method'!$B$20,"Medium","Low"))))
A20: R-19 | J20: =IF(OR(H20="",I20=""),"",H20*I20) | K20: =IF(J20="","",IF(J20>='Scoring Method'!$B$22,"Critical",IF(J20>='Scoring Method'!$B$21,"High",IF(J20>='Scoring Method'!$B$20,"Medium","Low")))) | P20: =IF(K20="","",IF(K20="Critical","Immediate (30 days)",IF(K20="High","Short term (60 days)",IF(K20="Medium","Medium term (90 days)","Monitor")))) | S20: =IF(OR(Q20="",R20=""),"",Q20*R20) | T20: =IF(S20="","",IF(S20>='Scoring Method'!$B$22,"Critical",IF(S20>='Scoring Method'!$B$21,"High",IF(S20>='Scoring Method'!$B$20,"Medium","Low"))))
A21: R-20 | J21: =IF(OR(H21="",I21=""),"",H21*I21) | K21: =IF(J21="","",IF(J21>='Scoring Method'!$B$22,"Critical",IF(J21>='Scoring Method'!$B$21,"High",IF(J21>='Scoring Method'!$B$20,"Medium","Low")))) | P21: =IF(K21="","",IF(K21="Critical","Immediate (30 days)",IF(K21="High","Short term (60 days)",IF(K21="Medium","Medium term (90 days)","Monitor")))) | S21: =IF(OR(Q21="",R21=""),"",Q21*R21) | T21: =IF(S21="","",IF(S21>='Scoring Method'!$B$22,"Critical",IF(S21>='Scoring Method'!$B$21,"High",IF(S21>='Scoring Method'!$B$20,"Medium","Low"))))
A22: R-21 | J22: =IF(OR(H22="",I22=""),"",H22*I22) | K22: =IF(J22="","",IF(J22>='Scoring Method'!$B$22,"Critical",IF(J22>='Scoring Method'!$B$21,"High",IF(J22>='Scoring Method'!$B$20,"Medium","Low")))) | P22: =IF(K22="","",IF(K22="Critical","Immediate (30 days)",IF(K22="High","Short term (60 days)",IF(K22="Medium","Medium term (90 days)","Monitor")))) | S22: =IF(OR(Q22="",R22=""),"",Q22*R22) | T22: =IF(S22="","",IF(S22>='Scoring Method'!$B$22,"Critical",IF(S22>='Scoring Method'!$B$21,"High",IF(S22>='Scoring Method'!$B$20,"Medium","Low"))))
A23: R-22 | J23: =IF(OR(H23="",I23=""),"",H23*I23) | K23: =IF(J23="","",IF(J23>='Scoring Method'!$B$22,"Critical",IF(J23>='Scoring Method'!$B$21,"High",IF(J23>='Scoring Method'!$B$20,"Medium","Low")))) | P23: =IF(K23="","",IF(K23="Critical","Immediate (30 days)",IF(K23="High","Short term (60 days)",IF(K23="Medium","Medium term (90 days)","Monitor")))) | S23: =IF(OR(Q23="",R23=""),"",Q23*R23) | T23: =IF(S23="","",IF(S23>='Scoring Method'!$B$22,"Critical",IF(S23>='Scoring Method'!$B$21,"High",IF(S23>='Scoring Method'!$B$20,"Medium","Low"))))
A24: R-23 | J24: =IF(OR(H24="",I24=""),"",H24*I24) | K24: =IF(J24="","",IF(J24>='Scoring Method'!$B$22,"Critical",IF(J24>='Scoring Method'!$B$21,"High",IF(J24>='Scoring Method'!$B$20,"Medium","Low")))) | P24: =IF(K24="","",IF(K24="Critical","Immediate (30 days)",IF(K24="High","Short term (60 days)",IF(K24="Medium","Medium term (90 days)","Monitor")))) | S24: =IF(OR(Q24="",R24=""),"",Q24*R24) | T24: =IF(S24="","",IF(S24>='Scoring Method'!$B$22,"Critical",IF(S24>='Scoring Method'!$B$21,"High",IF(S24>='Scoring Method'!$B$20,"Medium","Low"))))
A25: R-24 | J25: =IF(OR(H25="",I25=""),"",H25*I25) | K25: =IF(J25="","",IF(J25>='Scoring Method'!$B$22,"Critical",IF(J25>='Scoring Method'!$B$21,"High",IF(J25>='Scoring Method'!$B$20,"Medium","Low")))) | P25: =IF(K25="","",IF(K25="Critical","Immediate (30 days)",IF(K25="High","Short term (60 days)",IF(K25="Medium","Medium term (90 days)","Monitor")))) | S25: =IF(OR(Q25="",R25=""),"",Q25*R25) | T25: =IF(S25="","",IF(S25>='Scoring Method'!$B$22,"Critical",IF(S25>='Scoring Method'!$B$21,"High",IF(S25>='Scoring Method'!$B$20,"Medium","Low"))))
A26: R-25 | J26: =IF(OR(H26="",I26=""),"",H26*I26) | K26: =IF(J26="","",IF(J26>='Scoring Method'!$B$22,"Critical",IF(J26>='Scoring Method'!$B$21,"High",IF(J26>='Scoring Method'!$B$20,"Medium","Low")))) | P26: =IF(K26="","",IF(K26="Critical","Immediate (30 days)",IF(K26="High","Short term (60 days)",IF(K26="Medium","Medium term (90 days)","Monitor")))) | S26: =IF(OR(Q26="",R26=""),"",Q26*R26) | T26: =IF(S26="","",IF(S26>='Scoring Method'!$B$22,"Critical",IF(S26>='Scoring Method'!$B$21,"High",IF(S26>='Scoring Method'!$B$20,"Medium","Low"))))
A27: R-26 | J27: =IF(OR(H27="",I27=""),"",H27*I27) | K27: =IF(J27="","",IF(J27>='Scoring Method'!$B$22,"Critical",IF(J27>='Scoring Method'!$B$21,"High",IF(J27>='Scoring Method'!$B$20,"Medium","Low")))) | P27: =IF(K27="","",IF(K27="Critical","Immediate (30 days)",IF(K27="High","Short term (60 days)",IF(K27="Medium","Medium term (90 days)","Monitor")))) | S27: =IF(OR(Q27="",R27=""),"",Q27*R27) | T27: =IF(S27="","",IF(S27>='Scoring Method'!$B$22,"Critical",IF(S27>='Scoring Method'!$B$21,"High",IF(S27>='Scoring Method'!$B$20,"Medium","Low"))))
... A31: R-30 | J31: =IF(OR(H31="",I31=""),"",H31*I31) | K31: =IF(J31="","",IF(J31>='Scoring Method'!$B$22,"Critical",IF(J31>='Scoring Method'!$B$21,"High",IF(J31>='Scoring Method'!$B$20,"Medium","Low")))) | P31: =IF(K31="","",IF(K31="Critical","Immediate (30 days)",IF(K31="High","Short term (60 days)",IF(K31="Medium","Medium term (90 days)","Monitor")))) | S31: =IF(OR(Q31="",R31=""),"",Q31*R31) | T31: =IF(S31="","",IF(S31>='Scoring Method'!$B$22,"Critical",IF(S31>='Scoring Method'!$B$21,"High",IF(S31>='Scoring Method'!$B$20,"Medium","Low"))))

Sheet Summary
A1: Summary (calculated from the other sheets; nothing to type here)
A3: Rating | B3: Inherent risks | C3: Residual risks
A4: Critical | B4: =COUNTIF('Risk Register'!$K$2:$K$31,A4) -> 1 | C4: =COUNTIF('Risk Register'!$T$2:$T$31,A4) -> 0
A5: High | B5: =COUNTIF('Risk Register'!$K$2:$K$31,A5) -> 6 | C5: =COUNTIF('Risk Register'!$T$2:$T$31,A5) -> 0
A6: Medium | B6: =COUNTIF('Risk Register'!$K$2:$K$31,A6) -> 7 | C6: =COUNTIF('Risk Register'!$T$2:$T$31,A6) -> 6
A7: Low | B7: =COUNTIF('Risk Register'!$K$2:$K$31,A7) -> 0 | C7: =COUNTIF('Risk Register'!$T$2:$T$31,A7) -> 8
A8: Total risks | B8: =SUM(B4:B7) -> 14 | C8: =SUM(C4:C7) -> 14
A11: CSF Function | B11: Risks recorded | C11: Average maturity gap | D11: Average current maturity
A12: GOVERN | B12: =COUNTIF('Risk Register'!$F$2:$F$31,A12) -> 3 | C12: =IFERROR(AVERAGEIF('CSF Gap Assessment'!$A$2:$A$23,A12,'CSF Gap Assessment'!$F$2:$F$23),"") -> 1.6666667 | D12: =IFERROR(AVERAGEIF('CSF Gap Assessment'!$A$2:$A$23,A12,'CSF Gap Assessment'!$D$2:$D$23),"") -> 1.1666667
A13: IDENTIFY | B13: =COUNTIF('Risk Register'!$F$2:$F$31,A13) -> 0 | C13: =IFERROR(AVERAGEIF('CSF Gap Assessment'!$A$2:$A$23,A13,'CSF Gap Assessment'!$F$2:$F$23),"") -> 1.6666667 | D13: =IFERROR(AVERAGEIF('CSF Gap Assessment'!$A$2:$A$23,A13,'CSF Gap Assessment'!$D$2:$D$23),"") -> 1
A14: PROTECT | B14: =COUNTIF('Risk Register'!$F$2:$F$31,A14) -> 8 | C14: =IFERROR(AVERAGEIF('CSF Gap Assessment'!$A$2:$A$23,A14,'CSF Gap Assessment'!$F$2:$F$23),"") -> 1.8 | D14: =IFERROR(AVERAGEIF('CSF Gap Assessment'!$A$2:$A$23,A14,'CSF Gap Assessment'!$D$2:$D$23),"") -> 1.2
A15: DETECT | B15: =COUNTIF('Risk Register'!$F$2:$F$31,A15) -> 1 | C15: =IFERROR(AVERAGEIF('CSF Gap Assessment'!$A$2:$A$23,A15,'CSF Gap Assessment'!$F$2:$F$23),"") -> 2 | D15: =IFERROR(AVERAGEIF('CSF Gap Assessment'!$A$2:$A$23,A15,'CSF Gap Assessment'!$D$2:$D$23),"") -> 0.5
A16: RESPOND | B16: =COUNTIF('Risk Register'!$F$2:$F$31,A16) -> 1 | C16: =IFERROR(AVERAGEIF('CSF Gap Assessment'!$A$2:$A$23,A16,'CSF Gap Assessment'!$F$2:$F$23),"") -> 1.25 | D16: =IFERROR(AVERAGEIF('CSF Gap Assessment'!$A$2:$A$23,A16,'CSF Gap Assessment'!$D$2:$D$23),"") -> 1
A17: RECOVER | B17: =COUNTIF('Risk Register'!$F$2:$F$31,A17) -> 1 | C17: =IFERROR(AVERAGEIF('CSF Gap Assessment'!$A$2:$A$23,A17,'CSF Gap Assessment'!$F$2:$F$23),"") -> 2 | D17: =IFERROR(AVERAGEIF('CSF Gap Assessment'!$A$2:$A$23,A17,'CSF Gap Assessment'!$D$2:$D$23),"") -> 0.5
A19: Assets rated | B19: =COUNT(Assets!$F$2:$F$40) -> 14
A20: CSF categories scored | B20: =COUNT('CSF Gap Assessment'!$D$2:$D$23) -> 22
A21: Highest inherent score | B21: =IF(COUNT('Risk Register'!$J$2:$J$31)=0,"",MAX('Risk Register'!$J$2:$J$31)) -> 20
